Metadata-Version: 2.1
Name: image-template-overlay-apply
Version: 0.0.1
Summary: Takes an image that has placeholders and applies separate component issues to it.
Home-page: https://github.com/dsoprea/image_template_overlay_apply
Author: Dustin Oprea
Author-email: myselfasunder@gmail.com
License: MIT
Platform: UNKNOWN
